idr_accelerate/__init__.py
idr_accelerate/__main__.py
idr_accelerate/launcher.py
idr_accelerate/version.py
idr_accelerate-2.0.1.dist-info/METADATA
idr_accelerate-2.0.1.dist-info/WHEEL
idr_accelerate-2.0.1.dist-info/entry_points.txt
idr_accelerate-2.0.1.dist-info/top_level.txt
idr_accelerate-2.0.1.dist-info/RECORD
