Metadata-Version: 2.1
Name: idr-accelerate
Version: 2.0.1
Home-page: https://www.idris.fr
Author: IDRIS
Author-email: assist@idris.fr
License: MIT
Requires-Dist: accelerate
Requires-Dist: idr-torch >=2.0.1
Requires-Dist: packaging
Requires-Dist: torch
